telegram_task/__init__.py
telegram_task/line.py
telegram_task/president.py
telegram_task/samples.py
tests/__init__.py
tests/test_enterprise.py
tests/test_line.py
telegram_task-1.0.10.dist-info/METADATA
telegram_task-1.0.10.dist-info/WHEEL
telegram_task-1.0.10.dist-info/top_level.txt
telegram_task-1.0.10.dist-info/RECORD
