Metadata-Version: 2.1
Name: telegram-task
Version: 1.0.10
Summary: A telegram bot task manager wrapper.
Author: Arka Equities & Securities
Author-email: info@arkaequities.com
Classifier: Programming Language :: Python :: 3
Classifier: Operating System :: POSIX :: Linux
Classifier: Operating System :: MacOS :: MacOS X
Classifier: Operating System :: Microsoft :: Windows
Requires-Dist: python-telegram-bot[job-queue,socks] ==20.6
Requires-Dist: python-dotenv ==1.0.0
Requires-Dist: pytz ==2023.3.post1
